{
    "add_spending_set_custom_date": [
        {
            "text": "Сегодня",
            "callback_data": "spending_date_today"
        },
        {
            "text": "Своя дата",
            "callback_data": "spending_date_custom"
        }
    ],

    "plots_keyboard": [
        {
            "text": "Линейный график суммы затрат по датам",
            "callback_data": "plot_type_spendings_lineplot_by_date"
        },
        {
            "text": "Гистограмма суммы затрат по датам",
            "callback_data": "plot_type_spendings_barplot_by_date"
        },
        {
            "text": "Гистограмма суммы затрат в каждой из категорий",
            "callback_data": "plot_type_categories_barplot_by_currency"
        },
        {
            "text": "Диаграмма суммы затрат в каждой из категорий",
            "callback_data": "plot_type_categories_pieplot_by_currency"
        }
    ],

    "plot_date_filter_keyboard": [
        {
            "text": "Сегодня",
            "callback_data": "plot_date_today"
        },
        {
            "text": "Эта неделя",
            "callback_data": "plot_date_this_week"
        },
        {
            "text": "Этот месяц",
            "callback_data": "plot_date_this_month"
        },
        {
            "text": "Последние три месяца",
            "callback_data": "plot_date_three_months"
        },
        {
            "text": "Последние полгода",
            "callback_data": "plot_date_six_months"
        },
        {
            "text": "Последний год",
            "callback_data": "plot_date_this_year"
        }
    ],

    "verify_insertion_keyboard": [
        {
            "text": "Все правильно!",
            "callback_data": "verify_insertion_true"
        },

        {
            "text": "Неправильно!",
            "callback_data": "verify_insertion_false"
        }
    ],

    "verify_delete_all": [
        {
            "text": "Удалить все записи",
            "callback_data": "delete_all_true"
        },

        {
            "text": "Отменить удаление",
            "callback_data": "delete_all_false"
        }
    ]
}